README.md
setup.py
tencentcloud_iac_pulumi/__init__.py
tencentcloud_iac_pulumi/_inputs.py
tencentcloud_iac_pulumi/_utilities.py
tencentcloud_iac_pulumi/provider.py
tencentcloud_iac_pulumi/pulumi-plugin.json
tencentcloud_iac_pulumi/py.typed
tencentcloud_iac_pulumi.egg-info/PKG-INFO
tencentcloud_iac_pulumi.egg-info/SOURCES.txt
tencentcloud_iac_pulumi.egg-info/dependency_links.txt
tencentcloud_iac_pulumi.egg-info/not-zip-safe
tencentcloud_iac_pulumi.egg-info/requires.txt
tencentcloud_iac_pulumi.egg-info/top_level.txt
tencentcloud_iac_pulumi/address/__init__.py
tencentcloud_iac_pulumi/address/get_template_groups.py
tencentcloud_iac_pulumi/address/get_templates.py
tencentcloud_iac_pulumi/address/outputs.py
tencentcloud_iac_pulumi/address/template.py
tencentcloud_iac_pulumi/address/template_group.py
tencentcloud_iac_pulumi/antiddos/__init__.py
tencentcloud_iac_pulumi/antiddos/_inputs.py
tencentcloud_iac_pulumi/antiddos/cc_black_white_ip.py
tencentcloud_iac_pulumi/antiddos/cc_precision_policy.py
tencentcloud_iac_pulumi/antiddos/ddos_black_white_ip.py
tencentcloud_iac_pulumi/antiddos/ddos_geo_ip_block_config.py
tencentcloud_iac_pulumi/antiddos/ddos_speed_limit_config.py
tencentcloud_iac_pulumi/antiddos/default_alarm_threshold.py
tencentcloud_iac_pulumi/antiddos/get_basic_device_status.py
tencentcloud_iac_pulumi/antiddos/get_bgp_biz_trend.py
tencentcloud_iac_pulumi/antiddos/get_list_listener.py
tencentcloud_iac_pulumi/antiddos/get_overview_attack_trend.py
tencentcloud_iac_pulumi/antiddos/get_overview_cc_trend.py
tencentcloud_iac_pulumi/antiddos/get_overview_ddos_event_list.py
tencentcloud_iac_pulumi/antiddos/get_overview_ddos_trend.py
tencentcloud_iac_pulumi/antiddos/get_overview_index.py
tencentcloud_iac_pulumi/antiddos/get_pending_risk_info.py
tencentcloud_iac_pulumi/antiddos/ip_alarm_threshold_config.py
tencentcloud_iac_pulumi/antiddos/outputs.py
tencentcloud_iac_pulumi/antiddos/packet_filter_config.py
tencentcloud_iac_pulumi/antiddos/port_acl_config.py
tencentcloud_iac_pulumi/antiddos/scheduling_domain_user_name.py
tencentcloud_iac_pulumi/apigateway/__init__.py
tencentcloud_iac_pulumi/apigateway/_inputs.py
tencentcloud_iac_pulumi/apigateway/api.py
tencentcloud_iac_pulumi/apigateway/api_app.py
