Metadata-Version: 2.1
Name: tencentcloud-iac-pulumi
Version: 0.2.1
Summary: A Pulumi package for creating and managing Tencent Cloud resources.
Home-page: https://www.pulumi.com
License: Apache-2.0
Project-URL: Repository, https://github.com/tencentcloudstack/pulumi-tencentcloud
Keywords: pulumi tencentcloud category/cloud
Platform: UNKNOWN
Requires-Python: >=3.8
